geography/__init__.py
geography/admin.py
geography/apps.py
geography/conf.py
geography/pagination.py
geography/urls.py
geography/bin/hi/clipped_hi.cpg
geography/bin/hi/clipped_hi.dbf
geography/bin/hi/clipped_hi.prj
geography/bin/hi/clipped_hi.qpj
geography/bin/hi/clipped_hi.shp
geography/bin/hi/clipped_hi.shx
geography/bin/pa/clipped_pa.cpg
geography/bin/pa/clipped_pa.dbf
geography/bin/pa/clipped_pa.prj
geography/bin/pa/clipped_pa.qpj
geography/bin/pa/clipped_pa.shp
geography/management/__init__.py
geography/management/commands/__init__.py
geography/management/commands/bake_geography.py
geography/management/commands/bootstrap_geography.py
geography/management/commands/bootstrap_geom_hi.py
geography/management/commands/bootstrap_geom_pa.py
geography/management/commands/bake/__init__.py
geography/management/commands/bake/_arguments.py
geography/management/commands/bake/_attributes.py
geography/management/commands/bake/geometries/__init__.py
geography/management/commands/bake/geometries/_district.py
geography/management/commands/bake/geometries/_state.py
geography/management/commands/bootstrap/__init__.py
geography/management/commands/bootstrap/_arguments.py
geography/management/commands/bootstrap/_attributes.py
geography/management/commands/bootstrap/_toposimplify.py
geography/management/commands/bootstrap/aggregate_shapes/__init__.py
geography/management/commands/bootstrap/aggregate_shapes/district/__init__.py
geography/management/commands/bootstrap/aggregate_shapes/district/_county.py
geography/management/commands/bootstrap/aggregate_shapes/state/__init__.py
geography/management/commands/bootstrap/aggregate_shapes/state/_county.py
geography/management/commands/bootstrap/aggregate_shapes/state/_district.py
geography/management/commands/bootstrap/aggregate_shapes/state/_township.py
geography/management/commands/bootstrap/download/__init__.py
geography/management/commands/bootstrap/download/_county.py
politico_civic_geography-0.5.1.dist-info/METADATA
politico_civic_geography-0.5.1.dist-info/RECORD
politico_civic_geography-0.5.1.dist-info/WHEEL
politico_civic_geography-0.5.1.dist-info/top_level.txt
