Metadata-Version: 2.1
Name: politico-civic-geography
Version: 0.5.1
Summary: UNKNOWN
Home-page: https://github.com/The-Politico/politico-civic-geography
Author: POLITICO interactive news
Author-email: interactives@politico.com
License: MIT
Platform: UNKNOWN
Classifier: Development Status :: 3 - Alpha
Classifier: Framework :: Django
Classifier: Framework :: Django :: 2.0
Classifier: Intended Audience :: Developers
Classifier: Intended Audience :: Information Technology
Classifier: License :: OSI Approved :: MIT License
Classifier: Operating System :: OS Independent
Classifier: Programming Language :: Python :: 3
Classifier: Programming Language :: Python :: 3.5
Classifier: Programming Language :: Python :: 3.6
Classifier: Topic :: Internet :: WWW/HTTP
Provides-Extra: test
Provides-Extra: dev
Requires-Dist: boto3
Requires-Dist: census
Requires-Dist: DictObject
Requires-Dist: django
Requires-Dist: djangorestframework
Requires-Dist: dj-database-url
Requires-Dist: geojson
Requires-Dist: psycopg2
Requires-Dist: pyshp
Requires-Dist: shapely
Requires-Dist: stringcase
Requires-Dist: tqdm
Requires-Dist: us
Provides-Extra: dev
Requires-Dist: sphinx; extra == 'dev'
Requires-Dist: sphinxcontrib-django; extra == 'dev'
Requires-Dist: sphinx-rtd-theme; extra == 'dev'
Provides-Extra: test
Requires-Dist: pytest; extra == 'test'
